[
    {
      "ParameterKey": "TransferServerStack",
      "ParameterValue": "community-sftp"
    }, 
    {
      "ParameterKey": "BucketStack",
      "ParameterValue": "community-bucket"
    },
    {
        "ParameterKey": "UserName",
        "ParameterValue": "user-example"
    },
    {
        "ParameterKey": "PublicKey",
        "ParameterValue": "user-example public key that starts with ssh-rsa ..."
    },
    {
        "ParameterKey": "CidrIp",
        "ParameterValue": "52.95.4.0/24"
    } 
  ]

